ln_scikit/__init__.py
ln_scikit/estimator.py
ln_scikit/scikit_input.py
ln_scikit/scikit_output.py
LN_Scikit-1.0.0.dist-info/AUTHORS.rst
LN_Scikit-1.0.0.dist-info/LICENSE
LN_Scikit-1.0.0.dist-info/METADATA
LN_Scikit-1.0.0.dist-info/WHEEL
LN_Scikit-1.0.0.dist-info/entry_points.txt
LN_Scikit-1.0.0.dist-info/top_level.txt
LN_Scikit-1.0.0.dist-info/zip-safe
LN_Scikit-1.0.0.dist-info/RECORD
