Metadata-Version: 2.1
Name: LN-Scikit
Version: 1.0.0
Summary: LiveNodes: node based live streaming sensor/data and visualization suite.
Author-email: Yale Hartmann <yale.hartmann@uni-bremen.de>
License: GNU GENERAL PUBLIC LICENSE
License-File: LICENSE
License-File: AUTHORS.rst
Requires-Dist: livenodes>=0.12.1b1
Requires-Dist: ln-ports>=0.12.1b1
Requires-Dist: scikit-learn>=1.3.2
Provides-Extra: dev
Requires-Dist: tox; extra == "dev"
Requires-Dist: pytest>=7.0.1; extra == "dev"
